am4894airflowutils/__init__.py
am4894airflowutils/airflow.py
am4894airflowutils/bigquery.py
am4894airflowutils/dev.py
am4894airflowutils/google.py
am4894airflowutils/utils.py
am4894airflowutils/gainsight/__init__.py
am4894airflowutils/gainsight/airflow/README.md
am4894airflowutils/gainsight/airflow/__init__.py
am4894airflowutils/gainsight/airflow/hooks.py
am4894airflowutils/gainsight/airflow/operators.py
am4894airflowutils-0.0.2.dist-info/METADATA
am4894airflowutils-0.0.2.dist-info/WHEEL
am4894airflowutils-0.0.2.dist-info/licenses/LICENSE
am4894airflowutils-0.0.2.dist-info/RECORD
